prj3_coded-lock/lock.v
/*
基本功能：
    1.基本开锁功能:输入4位密码，按确认键开锁。   开锁后保持30s。 这里设置为3 cycle
    2.错误处理:连续3次输错密码后锁定3分钟。                     这里设置为3 cycle
    3.超级密码功能:输入6位超级密码后，可以重设4位开锁密码。
    4.取消功能:在输入过程中可以按取消键取消操作。
*/

module lock(
    input wire clk,
    input wire clr,
    input wire [3:0] din,       //数字键
    input wire cancel,          //取消键'*'
    input wire confirm,         //确定键'#'

    output reg unlock_ok,       //开锁,输出 1
    output reg reset_ok,        //成功重设密码，输出 1
    output reg locking          //输错密码死锁状态,输出 1
);

// 初始密码1234
reg [3:0] passwd0 = 1;
reg [3:0] passwd1 = 2;
reg [3:0] passwd2 = 3;
reg [3:0] passwd3 = 4;

// 超级密码230419
reg [3:0] superwd0 = 2;
reg [3:0] superwd1 = 3;
reg [3:0] superwd2 = 0;
reg [3:0] superwd3 = 4;
reg [3:0] superwd4 = 1;
reg [3:0] superwd5 = 9;

// 新密码
reg [3:0] newpasswd0 = 0, newpasswd1 = 0, newpasswd2 = 0, newpasswd3 = 0;
// 开启状态保持时间
reg [5:0] open_time = 0;
// 连续输错密码次数
reg [5:0] wrong_count = 0;
// 锁定状态保持时间
reg [5:0] lock_time = 0;
// 状态定义    没有用到next_state 寄存器
// 如果使用 always_ff 的形式，一个reg就够了，两个反而不好写
// 如果使用 显示dff+组合逻辑 的形式，next_state_s 定义为wire就行，写组合逻辑就行了
reg [3:0] present_state_s, next_state_s;
reg [4:0] present_state_t, next_state_t;

// 状态机S状态定义
localparam S0 = 3'b000, S1 = 3'b001, S2 = 3'b010, S3 = 3'b011;
localparam S4 = 3'b100, Open = 3'b101, Lock = 3'b110;

// 状态机T状态定义
localparam T0 = 5'b00000, T1 = 5'b00001, T2 = 5'b00010, T3 = 5'b00011, T4 = 5'b00100;
localparam T5 = 5'b00101, T6 = 5'b00110, T7 = 5'b00111, T8 = 5'b01000, T9 = 5'b01001;
localparam T10 = 5'b01010, T11 = 5'b01011, T12 = 5'b01100, T13 = 5'b01101, T14 = 5'b01110;
localparam T15 = 5'b01111, T16 = 5'b10000, T17 = 5'b10001, T18 = 5'b10010, T19 = 5'b10011;
localparam T20 = 5'b10100, OK = 5'b10101;

// 自定义宏定义
`define OPEN_TIME 6'd3;
`define LOCK_TIME 6'd3;

// 检测确认键和取消键  这里设置了两按键同时有效时，confirm优先
`define check(confirm, cancel, passwdn, Sn)  \
    begin \
        if (confirm) begin \
            if(present_state_t == T20) \    //改密码成功的情况，把错误次数清零
                wrong_count <= 0; \
            else if (wrong_count == 2) begin \  
                wrong_count <= 0; \
                present_state_s <= Lock; \
                lock_time <= `LOCK_TIME; \
                locking <= 1; \
            end \
            else  begin \
                wrong_count <= wrong_count + 1 ; \
                present_state_s <= S0; \
            end \
        end \
        else if (cancel) \
            present_state_s <= S0; \
        else if (din == passwdn) \
            present_state_s <= Sn; \
        else \
            present_state_s <= S0; \
    end
// 超级密码输入
`define superwd_in(superwdn,Tn)  \
    begin \
        if (din == superwdn) present_state_t <= Tn; \
        else present_state_t <= T0; \
    end
// 新密码输入
`define newpasswd_in(newpasswdn,Tn)  \
    begin \
        newpasswdn <= din; \
        present_state_t <= Tn; \
    end
// 确认新密码
`define confirm_newpasswd(newpasswdn,Tn) \
    begin \
    if (din == newpasswdn) present_state_t <= Tn; \
    else present_state_t <= T0; \
    end 

/*
    实际密码锁应该有按键输入检测来作为逻辑更新触发条件， 
    这里是tb_lock.v中的按键输入激励设置得和工作频率一致，简化了
*/
// 状态机S   
always @(posedge clk or posedge clr) begin
    if (clr) begin
        present_state_s <= S0;
        unlock_ok <= 0;
        open_time <= 0;
        wrong_count <= 0;

        locking <= 0;  // 死锁状态
    end else begin
        case (present_state_s)    // 状态转移
            S0: `check(confirm, cancel,passwd0,S1)
            S1: `check(confirm,cancel,passwd1,S2)            
            S2: `check(confirm, cancel,passwd2,S3)            
            S3: `check(confirm, cancel,passwd3,S4)            
            // s4，对于用户来说与前四个状态并没有区别
            S4: begin
                if (confirm) begin
                    present_state_s <= Open;
                    unlock_ok <= 1;
                    open_time <= `OPEN_TIME;  // 开锁保持时间
                end
                else 
                    present_state_s <= S0;
            end
            Open: begin
                if (open_time == 1) begin
                    unlock_ok <= 0;
                    present_state_s <= S0;
                end 
                else begin
                    open_time <= open_time - 1;
                    present_state_s <= Open;
                end
            end
            Lock: begin
                if (lock_time == 1) begin
                    locking <= 0;       // 解除死锁状态
                    present_state_s <= S0;
                end 
                else begin
                    lock_time <= lock_time - 1;
                    present_state_s <= Lock;
                end
            end
            default: present_state_s <= S0;
        endcase
    end
end

// 状态机T
always @(posedge clk or posedge clr) begin
    if (clr) begin
        present_state_t <= T0;
        reset_ok <= 0;
    end else begin
        // 这里 cancel 逻辑可以抽出来
        if (cancel) 
            present_state_t <= T0;
        else begin
            case (present_state_t)
            // 输入超级密码 230419 两遍；
            T0: `superwd_in(superwd0,T1)
            T1: `superwd_in(superwd1,T2)
            T2: `superwd_in(superwd2,T3)
            T3: `superwd_in(superwd3,T4)
            T4: `superwd_in(superwd4,T5)
            T5: `superwd_in(superwd5,T6)
            T6: `superwd_in(superwd0,T7)
            T7: `superwd_in(superwd1,T8)
            T8: `superwd_in(superwd2,T9)
            T9: `superwd_in(superwd3,T10)
            T10:`superwd_in(superwd4,T11) 
            T11:`superwd_in(superwd5,T12) 
            // 输入新密码
            T12: `newpasswd_in(newpasswd0,T13)
            T13: `newpasswd_in(newpasswd1,T14)
            T14: `newpasswd_in(newpasswd2,T15)
            T15: `newpasswd_in(newpasswd3,T16)
            // 确认新密码
            T16: `confirm_newpasswd(newpasswd0,T17)
            T17: `confirm_newpasswd(newpasswd1,T18)
            T18: `confirm_newpasswd(newpasswd2,T19)
            T19: `confirm_newpasswd(newpasswd3,T20)
            // 这里考虑实际功能需求，等待confirm键确认,cancel键取消; 屏蔽数字输入
            T20: begin
                if (confirm) begin
                    present_state_t <= OK;
                    reset_ok <= 1;
                end                     
                else present_state_t <= T20;
            end
            OK: begin
                passwd0 <= newpasswd0;
                passwd1 <= newpasswd1;
                passwd2 <= newpasswd2;
                passwd3 <= newpasswd3;
                reset_ok <= 0;
                present_state_t <= T0;
                // 重设新密码应该有这个逻辑的，但这个写法会多驱动赋值， 
                // 可以写在第一个状态机 S 里面; 还是单独拿出来写比较好
                // wrong_count <= 0;
            end
            default: present_state_t <= T0;
        endcase
        end
    end
end



endmodule

prj3_coded-lock/tb_lock.v
`timescale 1ns / 1ps

module tb_lock();

reg clr;
reg [3:0] din;	//数字键
reg cancel;	    //取消键'*'
reg confirm;	//确定键'#'
wire unlock_ok;	//开锁,输出 1
wire reset_ok;	//成功重设密码，输出 1
wire locking;	//输错密码锁定状态,输出 1


reg clk;
always #10 clk = ~clk;	//晶振周期 20ns


/* 仿真测试 
基本开锁功能测试：
    依次输入正确的密码 1 2 3 4，然后按确认键，验证是否成功开锁。
错误密码输入测试：
    依次输入错误的密码 1 2 3 5，然后按确认键，验证是否无法开锁。
超级密码功能测试：
    依次输入超级密码 230419 两次，
    然后输入新密码 6789 两次，验证是否成功修改密码。
连续输错密码测试：
    连续输入错误密码 1234 三次，验证是否进入锁定状态。
锁定状态测试：
    在锁定状态下，输入任何密码 6789，验证是否无法开锁。
取消功能测试：  
    在输入过程中按取消键，验证是否取消操作。

*/

initial begin
clk <= 0;
confirm <= 0;
din <= 0;
cancel <= 0;
clr <= 1;

#30
clr <= 0;
#40
//依次输入 1 2 3 4 确认,成功开锁
    din <= 1;
    #20
    din <= 2;
    #20
    din <= 3;
    #20
    din <= 4;

    #20
    din <= 0;
    confirm <= 1;
    #20
    confirm <= 0;
    #20
    #20
    #20
    #20

//依次输入 1 2 3 5 确认,无法开锁

    din <= 1;
    #20
    din <= 2;
    #20
    din <= 3;
    #20
    din <= 5;
    #20
    din <= 0;
    confirm <= 1;
    #20
    confirm <= 0;
    din <= 1;
    #20
    din <= 0;
    #20
    #20
    #20
    #20

//依次输入 230419 230419 6789 6789 确认
//密码从默认的 1234 修改为 6789

    din <= 2; #20
    din <= 3; #20
    din <= 0; #20
    din <= 4; #20
    din <= 1; #20
    din <= 9; #20

    din <= 2; #20
    din <= 3; #20
    din <= 0; #20
    din <= 4; #20
    din <= 1; #20
    din <= 9; #20

    din <= 6; #20
    din <= 7; #20
    din <= 8; #20
    din <= 9; #20

    din <= 6; #20
    din <= 7; #20
    din <= 8; #20
    din <= 9; #20
    confirm <= 1; #20
    confirm <= 0; din <= 0; #20

//连续输入 3 次错误密码：
//1234 # 1234 # 1234 #
    din <= 1; confirm <= 0; #20
    din <= 2; #20
    din <= 3; #20
    din <= 4; #20

    din <= 0; confirm <= 1; #20
    din <= 1; confirm <= 0; #20
    din <= 2; #20
    din <= 3; #20
    din <= 4; #20
    
    din <= 0; confirm <= 1; #20
    din <= 1; confirm <= 0; #20
    din <= 2; #20
    din <= 3; #20
    din <= 4; #20
    din <= 0; confirm <= 1; #20


//连续输错三次后，进入 lock 状态，无法开锁

    din <= 6; confirm <= 0; #20
    din <= 7; #20
    din <= 8; #20
    din <= 9; #20
    din <= 0; confirm <= 1; #20

//中途取消 test
    din <= 6; confirm <= 0; #20
    din <= 7; #20
    din <= 8; #20
    cancel <= 1; din <= 0; #20
    din <= 9; cancel <= 0; #20
    din <= 0; confirm <= 1; #20
    confirm <= 0;

// 添加结束条件
    #100;
    $finish;
end

lock test_lock(
    .clk(clk),
    .clr(clr),
    .din(din),
    .confirm(confirm),
    .cancel(cancel),
    .unlock_ok(unlock_ok),
    .reset_ok(reset_ok),
    .locking(locking)
);


initial
begin            
    $dumpfile("wave.vcd");        //生成的vcd文件名称
    $dumpvars(0, tb_lock);    //tb模块名称
end

endmodule

prj3_coded-lock/wave.vcd
$date
	Mon Dec 23 14:39:53 2024
$end
$version
	Icarus Verilog
$end
$timescale
	1ps
$end
$scope module tb_lock $end
$var wire 1 ! unlock_ok $end
$var wire 1 " reset_ok $end
$var wire 1 # locking $end
$var reg 1 $ cancel $end
$var reg 1 % clk $end
$var reg 1 & clr $end
$var reg 1 ' confirm $end
$var reg 4 ( din [3:0] $end
$scope module test_lock $end
$var wire 1 $ cancel $end
$var wire 1 % clk $end
$var wire 1 & clr $end
$var wire 1 ' confirm $end
$var wire 4 ) din [3:0] $end
$var reg 6 * lock_time [5:0] $end
$var reg 1 # locking $end
$var reg 4 + newpasswd0 [3:0] $end
$var reg 4 , newpasswd1 [3:0] $end
$var reg 4 - newpasswd2 [3:0] $end
$var reg 4 . newpasswd3 [3:0] $end
$var reg 6 / open_time [5:0] $end
$var reg 4 0 passwd0 [3:0] $end
$var reg 4 1 passwd1 [3:0] $end
$var reg 4 2 passwd2 [3:0] $end
$var reg 4 3 passwd3 [3:0] $end
$var reg 4 4 present_state_s [3:0] $end
$var reg 5 5 present_state_t [4:0] $end
$var reg 1 " reset_ok $end
$var reg 4 6 superwd0 [3:0] $end
$var reg 4 7 superwd1 [3:0] $end
$var reg 4 8 superwd2 [3:0] $end
$var reg 4 9 superwd3 [3:0] $end
$var reg 4 : superwd4 [3:0] $end
$var reg 4 ; superwd5 [3:0] $end
$var reg 1 ! unlock_ok $end
$var reg 6 < wrong_count [5:0] $end
$upscope $end
$upscope $end
$enddefinitions $end
#0
$dumpvars
b0 <
b1001 ;
b1 :
b100 9
b0 8
b11 7
b10 6
b0 5
b0 4
b100 3
b11 2
b10 1
b1 0
b0 /
b0 .
b0 -
b0 ,
b0 +
b0 *
b0 )
b0 (
0'
1&
0%
0$
0#
0"
0!
$end
#10000
1%
#20000
0%
#30000
0&
1%
#40000
0%
#50000
1%
#60000
0%
#70000
b1 (
b1 )
1%
#80000
0%
#90000
b1 4
b10 (
b10 )
1%
#100000
0%
#110000
b10 4
b1 5
b11 (
b11 )
1%
#120000
0%
#130000
b10 5
b11 4
b100 (
b100 )
1%
#140000
0%
#150000
b100 4
b0 5
1'
b0 (
b0 )
1%
#160000
0%
#170000
b11 /
1!
b101 4
0'
1%
#180000
0%
#190000
b10 /
1%
#200000
0%
#210000
b1 /
1%
#220000
0%
#230000
b0 4
0!
1%
#240000
0%
#250000
b1 (
b1 )
1%
#260000
0%
#270000
b1 4
b10 (
b10 )
1%
#280000
0%
#290000
b1 5
b10 4
b11 (
b11 )
1%
#300000
0%
#310000
b11 4
b10 5
b101 (
b101 )
1%
#320000
0%
#330000
b0 5
b0 4
1'
b0 (
b0 )
1%
#340000
0%
#350000
b1 <
b1 (
b1 )
0'
1%
#360000
0%
#370000
b1 4
b0 (
b0 )
1%
#380000
0%
#390000
b0 4
1%
#400000
0%
#410000
1%
#420000
0%
#430000
1%
#440000
0%
#450000
b10 (
b10 )
1%
#460000
0%
#470000
b1 5
b11 (
b11 )
1%
#480000
0%
#490000
b10 5
b0 (
b0 )
1%
#500000
0%
#510000
b11 5
b100 (
b100 )
1%
#520000
0%
#530000
b100 5
b1 (
b1 )
1%
#540000
0%
#550000
b1 4
b101 5
b1001 (
b1001 )
1%
#560000
0%
#570000
b110 5
b0 4
b10 (
b10 )
1%
#580000
0%
#590000
b111 5
b11 (
b11 )
1%
#600000
0%
#610000
b1000 5
b0 (
b0 )
1%
#620000
0%
#630000
b1001 5
b100 (
b100 )
1%
#640000
0%
#650000
b1010 5
b1 (
b1 )
1%
#660000
0%
#670000
b1 4
b1011 5
b1001 (
b1001 )
1%
#680000
0%
#690000
b1100 5
b0 4
b110 (
b110 )
1%
#700000
0%
#710000
b1101 5
b110 +
b111 (
b111 )
1%
#720000
0%
#730000
b1110 5
b111 ,
b1000 (
b1000 )
1%
#740000
0%
#750000
b1111 5
b1000 -
b1001 (
b1001 )
1%
#760000
0%
#770000
b10000 5
b1001 .
b110 (
b110 )
1%
#780000
0%
#790000
b10001 5
b111 (
b111 )
1%
#800000
0%
#810000
b10010 5
b1000 (
b1000 )
1%
#820000
0%
#830000
b10011 5
b1001 (
b1001 )
1%
#840000
0%
#850000
b10100 5
1'
1%
#860000
0%
#870000
b0 <
1"
b10101 5
b0 (
b0 )
0'
1%
#880000
0%
#890000
b0 5
0"
b1001 3
b1000 2
b111 1
b110 0
b1 (
b1 )
1%
#900000
0%
#910000
b10 (
b10 )
1%
#920000
0%
#930000
b1 5
b11 (
b11 )
1%
#940000
0%
#950000
b10 5
b100 (
b100 )
1%
#960000
0%
#970000
b0 5
1'
b0 (
b0 )
1%
#980000
0%
#990000
b1 <
0'
b1 (
b1 )
1%
#1000000
0%
#1010000
b10 (
b10 )
1%
#1020000
0%
#1030000
b1 5
b11 (
b11 )
1%
#1040000
0%
#1050000
b10 5
b100 (
b100 )
1%
#1060000
0%
#1070000
b0 5
1'
b0 (
b0 )
1%
#1080000
0%
#1090000
b10 <
0'
b1 (
b1 )
1%
#1100000
0%
#1110000
b10 (
b10 )
1%
#1120000
0%
#1130000
b1 5
b11 (
b11 )
1%
#1140000
0%
#1150000
b10 5
b100 (
b100 )
1%
#1160000
0%
#1170000
b0 5
1'
b0 (
b0 )
1%
#1180000
0%
#1190000
1#
b11 *
b110 4
b0 <
0'
b110 (
b110 )
1%
#1200000
0%
#1210000
b10 *
b111 (
b111 )
1%
#1220000
0%
#1230000
b1 *
b1000 (
b1000 )
1%
#1240000
0%
#1250000
b0 4
0#
b1001 (
b1001 )
1%
#1260000
0%
#1270000
1'
b0 (
b0 )
1%
#1280000
0%
#1290000
b1 <
0'
b110 (
b110 )
1%
#1300000
0%
#1310000
b1 4
b111 (
b111 )
1%
#1320000
0%
#1330000
b10 4
b1000 (
b1000 )
1%
#1340000
0%
#1350000
b11 4
b0 (
b0 )
1$
1%
#1360000
0%
#1370000
b0 4
0$
b1001 (
b1001 )
1%
#1380000
0%
#1390000
1'
b0 (
b0 )
1%
#1400000
0%
#1410000
b10 <
0'
1%
